{
  "main": {
    "id": "36ab5ae9563cfb70",
    "type": "split",
    "children": [
      {
        "id": "f2422c11b5a8ab2e",
        "type": "tabs",
        "children": [
          {
            "id": "3d7dd6d7cf2e3a6c",
            "type": "leaf",
            "pinned": true,
            "state": {
              "type": "markdown",
              "state": {
                "file": "Literature Notes/ierusalimschy2006programming.md",
                "mode": "source",
                "source": false
              },
              "pinned": true
            }
          }
        ]
      },
      {
        "id": "44d8a7499feae2a9",
        "type": "tabs",
        "children": [
          {
            "id": "e87f4188d70e93a5",
            "type": "leaf",
            "pinned": true,
            "state": {
              "type": "pdf",
              "state": {
                "file": "Temp/Roberto Ierusalimschy - Programming in Lua-Lua.org (2016).pdf"
              },
              "pinned": true
            }
          }
        ]
      }
    ],
    "direction": "vertical"
  },
  "left": {
    "id": "a4e95e127f7caa16",
    "type": "split",
    "children": [
      {
        "id": "6bdbdf475517e9d4",
        "type": "tabs",
        "children": [
          {
            "id": "ab24a1bf7884ce64",
            "type": "leaf",
            "state": {
              "type": "file-explorer",
              "state": {
                "sortOrder": "alphabetical"
              }
            }
          },
          {
            "id": "3b297b892d7d6b4c",
            "type": "leaf",
            "state": {
              "type": "search",
              "state": {
                "query": "tag:#read",
                "matchingCase": false,
                "explainSearch": false,
                "collapseAll": false,
                "extraContext": false,
                "sortOrder": "alphabetical"
              }
            }
          },
          {
            "id": "5ba717ebb38d76b3",
            "type": "leaf",
            "state": {
              "type": "starred",
              "state": {}
            }
          },
          {
            "id": "fdb39e9dbfa42947",
            "type": "leaf",
            "state": {
              "type": "bookmarks",
              "state": {}
            }
          }
        ]
      }
    ],
    "direction": "horizontal",
    "width": 243
  },
  "right": {
    "id": "27476bb830b20702",
    "type": "split",
    "children": [
      {
        "id": "c2fd6a1c7a9291a2",
        "type": "tabs",
        "children": [
          {
            "id": "947e00a397461c9c",
            "type": "leaf",
            "state": {
              "type": "outline",
              "state": {
                "file": "Literature Notes/ierusalimschy2006programming.md"
              }
            }
          },
          {
            "id": "4b7fed80dbacb29c",
            "type": "leaf",
            "state": {
              "type": "tag",
              "state": {
                "sortOrder": "frequency",
                "useHierarchy": false
              }
            }
          },
          {
            "id": "345f44f03f2e1e0b",
            "type": "leaf",
            "state": {
              "type": "backlink",
              "state": {
                "file": "Literature Notes/ierusalimschy2006programming.md",
                "collapseAll": false,
                "extraContext": false,
                "sortOrder": "alphabetical",
                "showSearch": false,
                "searchQuery": "",
                "backlinkCollapsed": false,
                "unlinkedCollapsed": false
              }
            }
          },
          {
            "id": "f462ee544b5a1216",
            "type": "leaf",
            "state": {
              "type": "outgoing-link",
              "state": {
                "file": "Literature Notes/ierusalimschy2006programming.md",
                "linksCollapsed": true,
                "unlinkedCollapsed": true
              }
            }
          },
          {
            "id": "7603aa63579ba730",
            "type": "leaf",
            "state": {
              "type": "git-view",
              "state": {}
            }
          },
          {
            "id": "243fd2c679211764",
            "type": "leaf",
            "state": {
              "type": "all-properties",
              "state": {
                "sortOrder": "frequency"
              }
            }
          }
        ],
        "currentTab": 5
      }
    ],
    "direction": "horizontal",
    "width": 344.5,
    "collapsed": true
  },
  "left-ribbon": {
    "hiddenItems": {
      "switcher:Open quick switcher": false,
      "graph:Open graph view": false,
      "canvas:Create new canvas": false,
      "daily-notes:Open today's daily note": false,
      "templates:Insert template": false,
      "command-palette:Open command palette": false,
      "webpage-html-export:Export Vault to HTML": false
    }
  },
  "active": "3d7dd6d7cf2e3a6c",
  "lastOpenFiles": [
    "Temp/Roberto Ierusalimschy - Programming in Lua-Lua.org (2016).pdf",
    "index.md",
    "TIL/TIL - Rust.md",
    "Literature Notes/slaney2008locality.md",
    "Literature Notes/ooi2000indexing.md",
    "Literature Notes/o1996log.md",
    "Literature Notes/ierusalimschy2006programming.md",
    "Literature Notes/gray1984logic.md",
    "Literature Notes/doxsey2016introducing.md",
    "Literature Notes/bos2023rust.md",
    "Literature Notes/berchtold1998pyramid.md",
    "Literature Notes/arpacidusseau2018operating.md",
    "Glossary/Virtualization.md",
    "Glossary/VA-File.md",
    "Glossary/Pyramid Technique.md",
    "Glossary/Persistence.md",
    "Glossary/Locality Sensitive Hashing.md",
    "Glossary/iMinMax.md",
    "Glossary/Equi-Join.md",
    "Glossary/Curse of Dimensionality.md",
    "Glossary/Concurrency.md",
    "Glossary/Chebyshev Metric.md",
    "Misc/Lua/a",
    "Misc/Lua/chapter_7.lua",
    "Misc/Lua/chapter_6.lua",
    "Misc/Lua/chapter_5.lua",
    "Misc/Lua",
    "Misc",
    "Temp",
    "Temp Files",
    "untitled folder",
    "inbox/Testing Obsidian Smart Capture.md",
    "Literature Notes/bengio2017deep.md",
    "Glossary/Representation Learning.md",
    "Glossary/Machine Learning.md",
    "Private/Competitive Skyline Cliques/Untitled.canvas",
    "Images/Pasted image 20231007023516.png",
    "Images/Pasted image 20231006101737.png",
    "Images/Pasted image 20231006093513.png",
    "Images/Pasted image 20231006093236.png",
    "Images/Pasted image 20231006084519.png",
    "Images/Pasted image 20231004231945.png",
    "Images/Pasted image 20231004211907.png",
    "Graphics/Pasted Images/Pasted image 20230701134038.png",
    "Graphics/Pasted Images/Pasted image 20230701134019.png",
    "Graphics/Pasted Images/Pasted image 20230701090111.png",
    "Algorithmic Framework.canvas"
  ]
}